SoccerNet/DataLoader.py
SoccerNet/Downloader.py
SoccerNet/__init__.py
SoccerNet/utils.py
SoccerNet/Evaluation/ActionSpotting.py
SoccerNet/Evaluation/CameraCalibration.py
SoccerNet/Evaluation/DenseVideoCaptioning.py
SoccerNet/Evaluation/FieldCalibration.py
SoccerNet/Evaluation/GameStateReconstruction.py
SoccerNet/Evaluation/JerseyNumber.py
SoccerNet/Evaluation/MV_FoulRecognition.py
SoccerNet/Evaluation/ReIdentification.py
SoccerNet/Evaluation/ReplayGrounding.py
SoccerNet/Evaluation/Tracking.py
SoccerNet/Evaluation/utils.py
SoccerNet/Evaluation/utils_calibration.py
SoccerNet/data/BallChallenge.json
SoccerNet/data/BallTest.json
SoccerNet/data/BallTrain.json
SoccerNet/data/BallValid.json
SoccerNet/data/HeadersChallenge.json
SoccerNet/data/HeadersTest.json
SoccerNet/data/HeadersTrain.json
SoccerNet/data/HeadersValid.json
SoccerNet/data/SNMOT-challenge-nodet.txt
SoccerNet/data/SNMOT-challenge.txt
SoccerNet/data/SNMOT-test.txt
SoccerNet/data/SoccerNetCameraChangesChallenge.json
SoccerNet/data/SoccerNetCameraChangesTest.json
SoccerNet/data/SoccerNetCameraChangesTrain.json
SoccerNet/data/SoccerNetCameraChangesValid.json
SoccerNet/data/SoccerNetCaptionChallenge.json
SoccerNet/data/SoccerNetCaptionTest.json
SoccerNet/data/SoccerNetCaptionTrain.json
SoccerNet/data/SoccerNetCaptionValid.json
SoccerNet/data/SoccerNetFramesChallenge.json
SoccerNet/data/SoccerNetFramesTest.json
SoccerNet/data/SoccerNetFramesTrain.json
SoccerNet/data/SoccerNetFramesValid.json
SoccerNet/data/SoccerNetGamesChallenge.json
SoccerNet/data/SoccerNetGamesTest.json
SoccerNet/data/SoccerNetGamesTrain.json
SoccerNet/data/SoccerNetGamesValid.json
SoccerNet-0.1.61.dist-info/LICENSE
SoccerNet-0.1.61.dist-info/METADATA
SoccerNet-0.1.61.dist-info/WHEEL
SoccerNet-0.1.61.dist-info/top_level.txt
SoccerNet-0.1.61.dist-info/RECORD
