Metadata-Version: 2.1
Name: SoccerNet
Version: 0.1.61
Summary: SoccerNet SDK
Home-page: https://github.com/SoccerNet/SoccerNet
Author: Silvio Giancola
Author-email: silvio.giancola@kaust.edu.sa
License: MIT
Keywords: SoccerNet,SDK,Spotting,Football,Soccer,Video
Classifier: Development Status :: 3 - Alpha
Classifier: Intended Audience :: Developers
Classifier: Topic :: Software Development :: Build Tools
Classifier: License :: OSI Approved :: MIT License
Classifier: Programming Language :: Python :: 3
Classifier: Programming Language :: Python :: 3.7
Classifier: Programming Language :: Python :: 3.8
Classifier: Programming Language :: Python :: 3.9
Classifier: Programming Language :: Python :: 3.10
Classifier: Programming Language :: Python :: 3.11
Classifier: Programming Language :: Python :: 3.12
License-File: LICENSE
Requires-Dist: tqdm
Requires-Dist: scikit-video
Requires-Dist: matplotlib
Requires-Dist: google-measurement-protocol
Requires-Dist: pycocoevalcap
Requires-Dist: huggingface-hub[cli]
